hurahura/__init__.py
hurahura/mi_config.py
hurahura/mi_subject.py
hurahura/mi_utils.py
hurahura/miresearch.conf
hurahura/miresearch_main.py
hurahura/miresearch_watchdog.py
hurahura/miresearchui/README.md
hurahura/miresearchui/__init__.py
hurahura/miresearchui/local_directory_picker.py
hurahura/miresearchui/mainUI.py
hurahura/miresearchui/miui_helpers.py
hurahura/miresearchui/miui_settings_page.py
hurahura/miresearchui/subjectUI.py
hurahura-0.1.33.dist-info/METADATA
hurahura-0.1.33.dist-info/WHEEL
hurahura-0.1.33.dist-info/entry_points.txt
hurahura-0.1.33.dist-info/licenses/LICENSE
hurahura-0.1.33.dist-info/RECORD
