Metadata-Version: 2.4
Name: hurahura
Version: 0.1.33
Summary: Medical Imaging Research structuring and automation
Project-URL: Homepage, https://github.com/fraser29/hurahura
Author-email: "Fraser M. Callaghan" <callaghan.fm@gmail.com>
License: MIT
License-File: LICENSE
Keywords: ct,dicom,imaging,medical,mri
Classifier: License :: OSI Approved :: MIT License
Classifier: Programming Language :: Python
Classifier: Programming Language :: Python :: 3
Classifier: Programming Language :: Python :: 3.9
Classifier: Programming Language :: Python :: Implementation :: CPython
Classifier: Programming Language :: Python :: Implementation :: PyPy
Requires-Python: >=3.9.0
Requires-Dist: ngawari>=0.1.8
Requires-Dist: nicegui
Requires-Dist: numpy
Requires-Dist: pandas
Requires-Dist: spydcmtk>=1.2.10
Requires-Dist: watchdog
